kl_mcp_client/__init__.py
kl_mcp_client/__version__.py
kl_mcp_client/client.py
kl_mcp_client/tools.py
kl_mcp_client/asyncio/__init__.py
kl_mcp_client/asyncio/client.py
kl_mcp_client/asyncio/tools.py
kl_mcp_client-2.1.15.dist-info/METADATA
kl_mcp_client-2.1.15.dist-info/WHEEL
kl_mcp_client-2.1.15.dist-info/top_level.txt
kl_mcp_client-2.1.15.dist-info/RECORD
