Metadata-Version: 2.4
Name: kl-mcp-client
Version: 2.1.15
Summary: MCP Client for Python
Author-email: Kyle <hngan.it@gmail.com>
License: MIT
Requires-Python: >=3.8
Requires-Dist: requests>=2.32.5
Requires-Dist: httpx>=0.28.1
